napalm_srl/__init__.py
napalm_srl/gnmi_pb2.py
napalm_srl/jsondiff.py
napalm_srl/srl.py
napalm_srl-1.0.5.dist-info/AUTHORS
napalm_srl-1.0.5.dist-info/LICENSE
napalm_srl-1.0.5.dist-info/METADATA
napalm_srl-1.0.5.dist-info/WHEEL
napalm_srl-1.0.5.dist-info/top_level.txt
napalm_srl-1.0.5.dist-info/RECORD
