Metadata-Version: 2.1
Name: napalm-srl
Version: 1.0.5
Summary: Network Automation and Programmability Abstraction Layer driver for Nokia SR Linux
Home-page: https://github.com/napalm-automation-community/napalm-srlinux
Author: Jose Valente
Author-email: Jose Valente <jose.valente@nokia.com>, Jeroen van Bemmel <jeroen.van_bemmel@nokia.com>
Project-URL: Homepage, https://github.com/napalm-automation-community/napalm-srlinux
Project-URL: Bug Tracker, https://github.com/napalm-automation-community/napalm-srlinux/issues
Classifier: Topic :: System :: Networking
Classifier: Programming Language :: Python :: 3
Classifier: Programming Language :: Python :: 3.8
Classifier: Programming Language :: Python :: 3.9
Classifier: Programming Language :: Python :: 3.10
Classifier: Programming Language :: Python :: 3.11
Classifier: Programming Language :: Python :: 3.12
Classifier: Natural Language :: English
Requires-Python: >=3.8
License-File: LICENSE
License-File: AUTHORS
Requires-Dist: napalm >=2.0.0
Requires-Dist: pip >=20.1.1
Requires-Dist: pytest >=5.4.3
Requires-Dist: setuptools >=47.3.1
Requires-Dist: paramiko >=2.7.1
Requires-Dist: grpcio
Requires-Dist: protobuf ==3.20.3
Requires-Dist: cryptography
Requires-Dist: urllib3
Provides-Extra: tests
Requires-Dist: pytest ; extra == 'tests'
Requires-Dist: ruff ; extra == 'tests'
